harpoon/__init__.py
harpoon/actions.py
harpoon/amazon.py
harpoon/collector.py
harpoon/container_manager.py
harpoon/errors.py
harpoon/executor.py
harpoon/formatter.py
harpoon/helpers.py
harpoon/task_finder.py
harpoon/version.py
harpoon/dockerpty/__init__.py
harpoon/dockerpty/io.py
harpoon/dockerpty/pty.py
harpoon/dockerpty/tty.py
harpoon/option_spec/__init__.py
harpoon/option_spec/authentication_objs.py
harpoon/option_spec/command_objs.py
harpoon/option_spec/command_specs.py
harpoon/option_spec/harpoon_specs.py
harpoon/option_spec/image_objs.py
harpoon/option_spec/image_specs.py
harpoon/option_spec/task_objs.py
harpoon/ship/__init__.py
harpoon/ship/builder.py
harpoon/ship/context.py
harpoon/ship/network.py
harpoon/ship/progress_stream.py
harpoon/ship/runner.py
harpoon/ship/syncer.py
harpoon/ship/builders/__init__.py
harpoon/ship/builders/base.py
harpoon/ship/builders/normal.py
harpoon/sphinx/__init__.py
harpoon/sphinx/show_specs.py
harpoon/sphinx/show_tasks.py
docker_harpoon-0.19.0.dist-info/METADATA
docker_harpoon-0.19.0.dist-info/WHEEL
docker_harpoon-0.19.0.dist-info/entry_points.txt
docker_harpoon-0.19.0.dist-info/licenses/LICENSE
docker_harpoon-0.19.0.dist-info/RECORD
