Metadata-Version: 2.3
Name: docker-harpoon
Version: 0.19.0
Summary: Opinionated wrapper around docker
Project-URL: Homepage, https://github.com/delfick/harpoon
Author-email: Stephen Moore <stephen@delfick.com>
License-Expression: MIT
License-File: LICENSE
Keywords: docker
Requires-Python: >=3.8
Requires-Dist: delfick-project==0.8.0
Requires-Dist: docker==7.1.0
Requires-Dist: humanize
Requires-Dist: rainbow-logging-handler==2.2.2
Requires-Dist: ruyaml==0.91.0
Provides-Extra: tests
Requires-Dist: noseofyeti[black]==2.4.8; extra == 'tests'
Requires-Dist: psutil==5.6.3; extra == 'tests'
Requires-Dist: pytest>=7.2.0; extra == 'tests'
